kndrpy/__init__.py
kndrpy-0.1.0.dist-info/METADATA
kndrpy-0.1.0.dist-info/WHEEL
kndrpy-0.1.0.dist-info/top_level.txt
kndrpy-0.1.0.dist-info/RECORD
