Metadata-Version: 2.1
Name: kndrpy
Version: 0.1.0
Summary: Intelligent document parsing and inference engine
Author-email: BSAM <bsamuel@amalgusglobal.com>
